{"labels": [{"name": "nucleus", "x1": 1, "y1": 95, "x2": 7, "y2": 108, "size": {"height": 256, "width": 256}}, {"name": "nucleus", "x1": 73, "y1": 131, "x2": 83, "y2": 155, "size": {"height": 256, "width": 256}}, {"name": "nucleus", "x1": 70, "y1": 232, "x2": 89, "y2": 240, "size": {"height": 256, "width": 256}}, {"name": "nucleus", "x1": 182, "y1": 1, "x2": 199, "y2": 9, "size": {"height": 256, "width": 256}}, {"name": "nucleus", "x1": 239, "y1": 4, "x2": 249, "y2": 16, "size": {"height": 256, "width": 256}}, {"name": "nucleus", "x1": 129, "y1": 211, "x2": 136, "y2": 221, "size": {"height": 256, "width": 256}}, {"name": "nucleus", "x1": 196, "y1": 205, "x2": 205, "y2": 216, "size": {"height": 256, "width": 256}}, {"name": "positive_cell", "x1": 95, "y1": 47, "x2": 109, "y2": 66, "size": {"height": 256, "width": 256}}, {"name": "nucleus", "x1": 41, "y1": 197, "x2": 49, "y2": 203, "size": {"height": 256, "width": 256}}, {"name": "nucleus", "x1": 174, "y1": 95, "x2": 182, "y2": 110, "size": {"height": 256, "width": 256}}, {"name": "nucleus", "x1": 1, "y1": 205, "x2": 11, "y2": 219, "size": {"height": 256, "width": 256}}, {"name": "nucleus", "x1": 95, "y1": 48, "x2": 105, "y2": 63, "size": {"height": 256, "width": 256}}, {"name": "positive_cell", "x1": 128, "y1": 205, "x2": 161, "y2": 225, "size": {"height": 256, "width": 256}}, {"name": "positive_cell", "x1": 1, "y1": 88, "x2": 9, "y2": 110, "size": {"height": 256, "width": 256}}, {"name": "nucleus", "x1": 249, "y1": 174, "x2": 255, "y2": 179, "size": {"height": 256, "width": 256}}, {"name": "positive_cell", "x1": 54, "y1": 221, "x2": 64, "y2": 243, "size": {"height": 256, "width": 256}}]}