{"labels": [{"name": "nucleus", "x1": 113, "y1": 56, "x2": 128, "y2": 69, "size": {"height": 256, "width": 256}}, {"name": "nucleus", "x1": 106, "y1": 42, "x2": 123, "y2": 51, "size": {"height": 256, "width": 256}}, {"name": "nucleus", "x1": 130, "y1": 135, "x2": 139, "y2": 145, "size": {"height": 256, "width": 256}}, {"name": "nucleus", "x1": 34, "y1": 46, "x2": 46, "y2": 66, "size": {"height": 256, "width": 256}}, {"name": "nucleus", "x1": 105, "y1": 151, "x2": 113, "y2": 155, "size": {"height": 256, "width": 256}}, {"name": "positive_cell", "x1": 30, "y1": 42, "x2": 47, "y2": 67, "size": {"height": 256, "width": 256}}]}