{"labels": [{"name": "nucleus", "x1": 238, "y1": 89, "x2": 247, "y2": 106, "size": {"height": 256, "width": 256}}, {"name": "nucleus", "x1": 155, "y1": 240, "x2": 176, "y2": 255, "size": {"height": 256, "width": 256}}, {"name": "nucleus", "x1": 82, "y1": 200, "x2": 110, "y2": 214, "size": {"height": 256, "width": 256}}, {"name": "nucleus", "x1": 170, "y1": 60, "x2": 193, "y2": 74, "size": {"height": 256, "width": 256}}, {"name": "nucleus", "x1": 112, "y1": 59, "x2": 128, "y2": 78, "size": {"height": 256, "width": 256}}]}