{"labels": [{"name": "nucleus", "x1": 26, "y1": 4, "x2": 36, "y2": 25, "size": {"height": 256, "width": 256}}, {"name": "nucleus", "x1": 8, "y1": 125, "x2": 18, "y2": 141, "size": {"height": 256, "width": 256}}, {"name": "nucleus", "x1": 228, "y1": 121, "x2": 234, "y2": 133, "size": {"height": 256, "width": 256}}, {"name": "nucleus", "x1": 14, "y1": 32, "x2": 25, "y2": 39, "size": {"height": 256, "width": 256}}, {"name": "nucleus", "x1": 54, "y1": 246, "x2": 63, "y2": 252, "size": {"height": 256, "width": 256}}, {"name": "nucleus", "x1": 187, "y1": 54, "x2": 198, "y2": 62, "size": {"height": 256, "width": 256}}, {"name": "nucleus", "x1": 16, "y1": 201, "x2": 27, "y2": 210, "size": {"height": 256, "width": 256}}, {"name": "nucleus", "x1": 0, "y1": 124, "x2": 4, "y2": 132, "size": {"height": 256, "width": 256}}, {"name": "nucleus", "x1": 7, "y1": 200, "x2": 18, "y2": 214, "size": {"height": 256, "width": 256}}, {"name": "nucleus", "x1": 7, "y1": 199, "x2": 26, "y2": 211, "size": {"height": 256, "width": 256}}, {"name": "nucleus", "x1": 232, "y1": 148, "x2": 242, "y2": 152, "size": {"height": 256, "width": 256}}, {"name": "positive_cell", "x1": 54, "y1": 246, "x2": 70, "y2": 255, "size": {"height": 256, "width": 256}}]}