{"labels": [{"name": "nucleus", "x1": 56, "y1": 238, "x2": 71, "y2": 250, "size": {"height": 256, "width": 256}}, {"name": "nucleus", "x1": 101, "y1": 153, "x2": 111, "y2": 174, "size": {"height": 256, "width": 256}}, {"name": "nucleus", "x1": 241, "y1": 196, "x2": 254, "y2": 211, "size": {"height": 256, "width": 256}}, {"name": "nucleus", "x1": 206, "y1": 179, "x2": 216, "y2": 190, "size": {"height": 256, "width": 256}}, {"name": "nucleus", "x1": 140, "y1": 124, "x2": 146, "y2": 156, "size": {"height": 256, "width": 256}}, {"name": "nucleus", "x1": 213, "y1": 93, "x2": 225, "y2": 119, "size": {"height": 256, "width": 256}}, {"name": "nucleus", "x1": 36, "y1": 190, "x2": 44, "y2": 204, "size": {"height": 256, "width": 256}}, {"name": "nucleus", "x1": 202, "y1": 22, "x2": 212, "y2": 46, "size": {"height": 256, "width": 256}}, {"name": "nucleus", "x1": 86, "y1": 111, "x2": 96, "y2": 140, "size": {"height": 256, "width": 256}}, {"name": "nucleus", "x1": 40, "y1": 37, "x2": 54, "y2": 58, "size": {"height": 256, "width": 256}}]}