{"labels": [{"name": "nucleus", "x1": 107, "y1": 95, "x2": 118, "y2": 107, "size": {"height": 256, "width": 256}}, {"name": "nucleus", "x1": 24, "y1": 130, "x2": 36, "y2": 156, "size": {"height": 256, "width": 256}}, {"name": "nucleus", "x1": 96, "y1": 107, "x2": 108, "y2": 116, "size": {"height": 256, "width": 256}}, {"name": "nucleus", "x1": 9, "y1": 17, "x2": 17, "y2": 33, "size": {"height": 256, "width": 256}}, {"name": "nucleus", "x1": 29, "y1": 186, "x2": 40, "y2": 193, "size": {"height": 256, "width": 256}}, {"name": "nucleus", "x1": 113, "y1": 239, "x2": 122, "y2": 255, "size": {"height": 256, "width": 256}}, {"name": "nucleus", "x1": 40, "y1": 209, "x2": 49, "y2": 220, "size": {"height": 256, "width": 256}}, {"name": "positive_cell", "x1": 162, "y1": 37, "x2": 189, "y2": 63, "size": {"height": 256, "width": 256}}]}