{"labels": [{"name": "positive_cell", "x1": 160, "y1": 3, "x2": 173, "y2": 16, "size": {"height": 256, "width": 256}}, {"name": "positive_cell", "x1": 24, "y1": 191, "x2": 36, "y2": 206, "size": {"height": 256, "width": 256}}, {"name": "positive_cell", "x1": 172, "y1": 6, "x2": 182, "y2": 18, "size": {"height": 256, "width": 256}}, {"name": "positive_cell", "x1": 163, "y1": 3, "x2": 180, "y2": 17, "size": {"height": 256, "width": 256}}, {"name": "nucleus", "x1": 143, "y1": 146, "x2": 150, "y2": 158, "size": {"height": 256, "width": 256}}, {"name": "nucleus", "x1": 249, "y1": 124, "x2": 254, "y2": 136, "size": {"height": 256, "width": 256}}, {"name": "nucleus", "x1": 111, "y1": 147, "x2": 120, "y2": 161, "size": {"height": 256, "width": 256}}, {"name": "nucleus", "x1": 219, "y1": 104, "x2": 225, "y2": 111, "size": {"height": 256, "width": 256}}, {"name": "nucleus", "x1": 9, "y1": 174, "x2": 15, "y2": 178, "size": {"height": 256, "width": 256}}, {"name": "nucleus", "x1": 97, "y1": 126, "x2": 109, "y2": 133, "size": {"height": 256, "width": 256}}, {"name": "nucleus", "x1": 174, "y1": 8, "x2": 181, "y2": 17, "size": {"height": 256, "width": 256}}]}