{"labels": [{"name": "nucleus", "x1": 32, "y1": 178, "x2": 41, "y2": 194, "size": {"height": 256, "width": 256}}, {"name": "nucleus", "x1": 234, "y1": 35, "x2": 243, "y2": 46, "size": {"height": 256, "width": 256}}, {"name": "nucleus", "x1": 29, "y1": 0, "x2": 42, "y2": 8, "size": {"height": 256, "width": 256}}, {"name": "nucleus", "x1": 177, "y1": 25, "x2": 183, "y2": 39, "size": {"height": 256, "width": 256}}, {"name": "nucleus", "x1": 218, "y1": 138, "x2": 226, "y2": 150, "size": {"height": 256, "width": 256}}, {"name": "nucleus", "x1": 237, "y1": 51, "x2": 245, "y2": 66, "size": {"height": 256, "width": 256}}, {"name": "positive_cell", "x1": 219, "y1": 48, "x2": 235, "y2": 64, "size": {"height": 256, "width": 256}}, {"name": "positive_cell", "x1": 31, "y1": 178, "x2": 47, "y2": 203, "size": {"height": 256, "width": 256}}, {"name": "nucleus", "x1": 16, "y1": 196, "x2": 27, "y2": 208, "size": {"height": 256, "width": 256}}, {"name": "positive_cell", "x1": 156, "y1": 151, "x2": 165, "y2": 183, "size": {"height": 256, "width": 256}}, {"name": "positive_cell", "x1": 4, "y1": 197, "x2": 28, "y2": 218, "size": {"height": 256, "width": 256}}, {"name": "nucleus", "x1": 155, "y1": 172, "x2": 164, "y2": 182, "size": {"height": 256, "width": 256}}, {"name": "nucleus", "x1": 48, "y1": 134, "x2": 58, "y2": 140, "size": {"height": 256, "width": 256}}, {"name": "nucleus", "x1": 4, "y1": 205, "x2": 14, "y2": 210, "size": {"height": 256, "width": 256}}]}