{"labels": [{"name": "nucleus", "x1": 146, "y1": 138, "x2": 154, "y2": 151, "size": {"height": 256, "width": 256}}, {"name": "nucleus", "x1": 185, "y1": 235, "x2": 197, "y2": 245, "size": {"height": 256, "width": 256}}, {"name": "nucleus", "x1": 84, "y1": 245, "x2": 102, "y2": 253, "size": {"height": 256, "width": 256}}, {"name": "nucleus", "x1": 20, "y1": 177, "x2": 30, "y2": 183, "size": {"height": 256, "width": 256}}, {"name": "nucleus", "x1": 146, "y1": 82, "x2": 153, "y2": 88, "size": {"height": 256, "width": 256}}, {"name": "nucleus", "x1": 124, "y1": 103, "x2": 139, "y2": 113, "size": {"height": 256, "width": 256}}, {"name": "nucleus", "x1": 152, "y1": 186, "x2": 163, "y2": 198, "size": {"height": 256, "width": 256}}, {"name": "nucleus", "x1": 54, "y1": 227, "x2": 62, "y2": 239, "size": {"height": 256, "width": 256}}, {"name": "nucleus", "x1": 48, "y1": 192, "x2": 57, "y2": 197, "size": {"height": 256, "width": 256}}]}