{"labels": [{"name": "nucleus", "x1": 101, "y1": 170, "x2": 118, "y2": 184, "size": {"height": 256, "width": 256}}, {"name": "nucleus", "x1": 188, "y1": 228, "x2": 202, "y2": 242, "size": {"height": 256, "width": 256}}, {"name": "nucleus", "x1": 43, "y1": 172, "x2": 53, "y2": 179, "size": {"height": 256, "width": 256}}, {"name": "positive_cell", "x1": 192, "y1": 64, "x2": 209, "y2": 86, "size": {"height": 256, "width": 256}}, {"name": "positive_cell", "x1": 1, "y1": 34, "x2": 16, "y2": 48, "size": {"height": 256, "width": 256}}, {"name": "nucleus", "x1": 2, "y1": 37, "x2": 12, "y2": 48, "size": {"height": 256, "width": 256}}, {"name": "nucleus", "x1": 0, "y1": 150, "x2": 4, "y2": 160, "size": {"height": 256, "width": 256}}, {"name": "nucleus", "x1": 95, "y1": 155, "x2": 104, "y2": 163, "size": {"height": 256, "width": 256}}, {"name": "positive_cell", "x1": 193, "y1": 67, "x2": 226, "y2": 101, "size": {"height": 256, "width": 256}}]}