{"labels": [{"name": "nucleus", "x1": 3, "y1": 228, "x2": 16, "y2": 240, "size": {"height": 256, "width": 256}}, {"name": "nucleus", "x1": 154, "y1": 103, "x2": 177, "y2": 110, "size": {"height": 256, "width": 256}}, {"name": "nucleus", "x1": 152, "y1": 34, "x2": 165, "y2": 44, "size": {"height": 256, "width": 256}}, {"name": "nucleus", "x1": 158, "y1": 25, "x2": 178, "y2": 31, "size": {"height": 256, "width": 256}}, {"name": "nucleus", "x1": 99, "y1": 120, "x2": 111, "y2": 131, "size": {"height": 256, "width": 256}}, {"name": "nucleus", "x1": 202, "y1": 98, "x2": 215, "y2": 105, "size": {"height": 256, "width": 256}}, {"name": "nucleus", "x1": 234, "y1": 72, "x2": 243, "y2": 82, "size": {"height": 256, "width": 256}}, {"name": "nucleus", "x1": 144, "y1": 143, "x2": 154, "y2": 167, "size": {"height": 256, "width": 256}}, {"name": "nucleus", "x1": 1, "y1": 25, "x2": 15, "y2": 47, "size": {"height": 256, "width": 256}}, {"name": "nucleus", "x1": 141, "y1": 215, "x2": 150, "y2": 223, "size": {"height": 256, "width": 256}}, {"name": "nucleus", "x1": 0, "y1": 148, "x2": 11, "y2": 156, "size": {"height": 256, "width": 256}}, {"name": "nucleus", "x1": 148, "y1": 179, "x2": 165, "y2": 201, "size": {"height": 256, "width": 256}}, {"name": "nucleus", "x1": 164, "y1": 206, "x2": 175, "y2": 213, "size": {"height": 256, "width": 256}}, {"name": "nucleus", "x1": 56, "y1": 156, "x2": 71, "y2": 170, "size": {"height": 256, "width": 256}}, {"name": "nucleus", "x1": 7, "y1": 219, "x2": 18, "y2": 227, "size": {"height": 256, "width": 256}}, {"name": "nucleus", "x1": 110, "y1": 219, "x2": 125, "y2": 232, "size": {"height": 256, "width": 256}}, {"name": "positive_cell", "x1": 108, "y1": 214, "x2": 126, "y2": 232, "size": {"height": 256, "width": 256}}, {"name": "nucleus", "x1": 94, "y1": 205, "x2": 112, "y2": 214, "size": {"height": 256, "width": 256}}, {"name": "nucleus", "x1": 191, "y1": 16, "x2": 206, "y2": 26, "size": {"height": 256, "width": 256}}, {"name": "nucleus", "x1": 22, "y1": 238, "x2": 29, "y2": 249, "size": {"height": 256, "width": 256}}, {"name": "nucleus", "x1": 210, "y1": 193, "x2": 215, "y2": 197, "size": {"height": 256, "width": 256}}, {"name": "nucleus", "x1": 83, "y1": 229, "x2": 93, "y2": 238, "size": {"height": 256, "width": 256}}, {"name": "nucleus", "x1": 145, "y1": 201, "x2": 154, "y2": 212, "size": {"height": 256, "width": 256}}, {"name": "nucleus", "x1": 136, "y1": 98, "x2": 147, "y2": 106, "size": {"height": 256, "width": 256}}, {"name": "nucleus", "x1": 234, "y1": 223, "x2": 241, "y2": 233, "size": {"height": 256, "width": 256}}, {"name": "nucleus", "x1": 224, "y1": 162, "x2": 234, "y2": 172, "size": {"height": 256, "width": 256}}, {"name": "nucleus", "x1": 91, "y1": 200, "x2": 107, "y2": 207, "size": {"height": 256, "width": 256}}, {"name": "nucleus", "x1": 130, "y1": 99, "x2": 147, "y2": 109, "size": {"height": 256, "width": 256}}, {"name": "nucleus", "x1": 147, "y1": 239, "x2": 151, "y2": 254, "size": {"height": 256, "width": 256}}]}