{"labels": [{"name": "positive_cell", "x1": 200, "y1": 200, "x2": 214, "y2": 217, "size": {"height": 256, "width": 256}}, {"name": "nucleus", "x1": 90, "y1": 39, "x2": 103, "y2": 46, "size": {"height": 256, "width": 256}}, {"name": "nucleus", "x1": 141, "y1": 20, "x2": 150, "y2": 31, "size": {"height": 256, "width": 256}}, {"name": "nucleus", "x1": 203, "y1": 190, "x2": 211, "y2": 197, "size": {"height": 256, "width": 256}}, {"name": "nucleus", "x1": 201, "y1": 201, "x2": 212, "y2": 217, "size": {"height": 256, "width": 256}}, {"name": "nucleus", "x1": 240, "y1": 191, "x2": 253, "y2": 203, "size": {"height": 256, "width": 256}}]}