{"labels": [{"name": "nucleus", "x1": 202, "y1": 13, "x2": 209, "y2": 32, "size": {"height": 256, "width": 256}}, {"name": "nucleus", "x1": 42, "y1": 136, "x2": 51, "y2": 152, "size": {"height": 256, "width": 256}}, {"name": "nucleus", "x1": 157, "y1": 202, "x2": 164, "y2": 216, "size": {"height": 256, "width": 256}}, {"name": "nucleus", "x1": 71, "y1": 99, "x2": 78, "y2": 116, "size": {"height": 256, "width": 256}}, {"name": "nucleus", "x1": 75, "y1": 55, "x2": 84, "y2": 70, "size": {"height": 256, "width": 256}}, {"name": "nucleus", "x1": 248, "y1": 141, "x2": 254, "y2": 162, "size": {"height": 256, "width": 256}}, {"name": "nucleus", "x1": 81, "y1": 146, "x2": 88, "y2": 169, "size": {"height": 256, "width": 256}}, {"name": "positive_cell", "x1": 178, "y1": 66, "x2": 194, "y2": 87, "size": {"height": 256, "width": 256}}]}