{"labels": [{"name": "nucleus", "x1": 50, "y1": 206, "x2": 63, "y2": 219, "size": {"height": 256, "width": 256}}, {"name": "nucleus", "x1": 180, "y1": 203, "x2": 197, "y2": 218, "size": {"height": 256, "width": 256}}, {"name": "nucleus", "x1": 128, "y1": 211, "x2": 138, "y2": 221, "size": {"height": 256, "width": 256}}, {"name": "nucleus", "x1": 101, "y1": 202, "x2": 109, "y2": 220, "size": {"height": 256, "width": 256}}, {"name": "nucleus", "x1": 63, "y1": 214, "x2": 75, "y2": 225, "size": {"height": 256, "width": 256}}, {"name": "nucleus", "x1": 81, "y1": 240, "x2": 89, "y2": 253, "size": {"height": 256, "width": 256}}, {"name": "nucleus", "x1": 122, "y1": 202, "x2": 129, "y2": 211, "size": {"height": 256, "width": 256}}]}