{"labels": [{"name": "positive_cell", "x1": 47, "y1": 207, "x2": 61, "y2": 230, "size": {"height": 256, "width": 256}}, {"name": "positive_cell", "x1": 59, "y1": 113, "x2": 68, "y2": 126, "size": {"height": 256, "width": 256}}, {"name": "positive_cell", "x1": 123, "y1": 8, "x2": 130, "y2": 14, "size": {"height": 256, "width": 256}}, {"name": "nucleus", "x1": 198, "y1": 228, "x2": 215, "y2": 236, "size": {"height": 256, "width": 256}}, {"name": "nucleus", "x1": 99, "y1": 9, "x2": 121, "y2": 19, "size": {"height": 256, "width": 256}}, {"name": "nucleus", "x1": 67, "y1": 195, "x2": 79, "y2": 206, "size": {"height": 256, "width": 256}}, {"name": "nucleus", "x1": 108, "y1": 152, "x2": 121, "y2": 159, "size": {"height": 256, "width": 256}}, {"name": "nucleus", "x1": 84, "y1": 13, "x2": 93, "y2": 27, "size": {"height": 256, "width": 256}}, {"name": "nucleus", "x1": 134, "y1": 115, "x2": 143, "y2": 126, "size": {"height": 256, "width": 256}}, {"name": "nucleus", "x1": 106, "y1": 80, "x2": 112, "y2": 88, "size": {"height": 256, "width": 256}}, {"name": "nucleus", "x1": 191, "y1": 87, "x2": 197, "y2": 94, "size": {"height": 256, "width": 256}}, {"name": "nucleus", "x1": 202, "y1": 239, "x2": 207, "y2": 244, "size": {"height": 256, "width": 256}}, {"name": "nucleus", "x1": 55, "y1": 208, "x2": 61, "y2": 220, "size": {"height": 256, "width": 256}}, {"name": "nucleus", "x1": 61, "y1": 114, "x2": 68, "y2": 125, "size": {"height": 256, "width": 256}}, {"name": "nucleus", "x1": 47, "y1": 219, "x2": 51, "y2": 231, "size": {"height": 256, "width": 256}}]}