{"labels": [{"name": "positive_cell", "x1": 113, "y1": 203, "x2": 150, "y2": 228, "size": {"height": 256, "width": 256}}, {"name": "positive_cell", "x1": 73, "y1": 82, "x2": 108, "y2": 114, "size": {"height": 256, "width": 256}}, {"name": "positive_cell", "x1": 103, "y1": 199, "x2": 115, "y2": 218, "size": {"height": 256, "width": 256}}, {"name": "nucleus", "x1": 45, "y1": 166, "x2": 62, "y2": 176, "size": {"height": 256, "width": 256}}, {"name": "nucleus", "x1": 129, "y1": 175, "x2": 147, "y2": 186, "size": {"height": 256, "width": 256}}, {"name": "nucleus", "x1": 75, "y1": 82, "x2": 106, "y2": 114, "size": {"height": 256, "width": 256}}, {"name": "nucleus", "x1": 171, "y1": 37, "x2": 189, "y2": 51, "size": {"height": 256, "width": 256}}, {"name": "nucleus", "x1": 55, "y1": 120, "x2": 67, "y2": 132, "size": {"height": 256, "width": 256}}, {"name": "nucleus", "x1": 104, "y1": 200, "x2": 114, "y2": 218, "size": {"height": 256, "width": 256}}, {"name": "nucleus", "x1": 95, "y1": 82, "x2": 108, "y2": 94, "size": {"height": 256, "width": 256}}, {"name": "nucleus", "x1": 147, "y1": 198, "x2": 161, "y2": 204, "size": {"height": 256, "width": 256}}]}