{"labels": [{"name": "nucleus", "x1": 129, "y1": 42, "x2": 146, "y2": 60, "size": {"height": 256, "width": 256}}, {"name": "nucleus", "x1": 93, "y1": 238, "x2": 111, "y2": 253, "size": {"height": 256, "width": 256}}, {"name": "nucleus", "x1": 28, "y1": 75, "x2": 47, "y2": 96, "size": {"height": 256, "width": 256}}, {"name": "nucleus", "x1": 98, "y1": 72, "x2": 115, "y2": 89, "size": {"height": 256, "width": 256}}, {"name": "nucleus", "x1": 230, "y1": 152, "x2": 245, "y2": 171, "size": {"height": 256, "width": 256}}, {"name": "nucleus", "x1": 60, "y1": 214, "x2": 79, "y2": 232, "size": {"height": 256, "width": 256}}, {"name": "nucleus", "x1": 226, "y1": 237, "x2": 249, "y2": 251, "size": {"height": 256, "width": 256}}, {"name": "nucleus", "x1": 150, "y1": 54, "x2": 163, "y2": 69, "size": {"height": 256, "width": 256}}, {"name": "nucleus", "x1": 41, "y1": 199, "x2": 51, "y2": 208, "size": {"height": 256, "width": 256}}, {"name": "nucleus", "x1": 33, "y1": 103, "x2": 56, "y2": 125, "size": {"height": 256, "width": 256}}, {"name": "nucleus", "x1": 195, "y1": 101, "x2": 218, "y2": 119, "size": {"height": 256, "width": 256}}, {"name": "nucleus", "x1": 194, "y1": 88, "x2": 210, "y2": 102, "size": {"height": 256, "width": 256}}, {"name": "nucleus", "x1": 223, "y1": 1, "x2": 235, "y2": 5, "size": {"height": 256, "width": 256}}, {"name": "positive_cell", "x1": 194, "y1": 95, "x2": 220, "y2": 120, "size": {"height": 256, "width": 256}}, {"name": "nucleus", "x1": 118, "y1": 33, "x2": 125, "y2": 43, "size": {"height": 256, "width": 256}}]}