{"labels": [{"name": "nucleus", "x1": 3, "y1": 202, "x2": 17, "y2": 211, "size": {"height": 256, "width": 256}}, {"name": "nucleus", "x1": 124, "y1": 24, "x2": 135, "y2": 37, "size": {"height": 256, "width": 256}}, {"name": "nucleus", "x1": 16, "y1": 183, "x2": 27, "y2": 194, "size": {"height": 256, "width": 256}}, {"name": "nucleus", "x1": 127, "y1": 149, "x2": 138, "y2": 158, "size": {"height": 256, "width": 256}}, {"name": "nucleus", "x1": 25, "y1": 58, "x2": 32, "y2": 69, "size": {"height": 256, "width": 256}}]}