{"labels": [{"name": "nucleus", "x1": 116, "y1": 226, "x2": 135, "y2": 242, "size": {"height": 256, "width": 256}}, {"name": "nucleus", "x1": 87, "y1": 146, "x2": 100, "y2": 161, "size": {"height": 256, "width": 256}}, {"name": "nucleus", "x1": 57, "y1": 57, "x2": 64, "y2": 68, "size": {"height": 256, "width": 256}}, {"name": "nucleus", "x1": 224, "y1": 192, "x2": 230, "y2": 206, "size": {"height": 256, "width": 256}}, {"name": "nucleus", "x1": 26, "y1": 102, "x2": 41, "y2": 110, "size": {"height": 256, "width": 256}}, {"name": "nucleus", "x1": 127, "y1": 243, "x2": 136, "y2": 252, "size": {"height": 256, "width": 256}}, {"name": "nucleus", "x1": 171, "y1": 64, "x2": 182, "y2": 79, "size": {"height": 256, "width": 256}}, {"name": "nucleus", "x1": 60, "y1": 34, "x2": 69, "y2": 42, "size": {"height": 256, "width": 256}}, {"name": "nucleus", "x1": 98, "y1": 133, "x2": 104, "y2": 144, "size": {"height": 256, "width": 256}}, {"name": "nucleus", "x1": 86, "y1": 177, "x2": 96, "y2": 189, "size": {"height": 256, "width": 256}}, {"name": "nucleus", "x1": 145, "y1": 241, "x2": 161, "y2": 254, "size": {"height": 256, "width": 256}}, {"name": "nucleus", "x1": 51, "y1": 78, "x2": 56, "y2": 84, "size": {"height": 256, "width": 256}}]}