{"labels": [{"name": "nucleus", "x1": 69, "y1": 81, "x2": 84, "y2": 95, "size": {"height": 256, "width": 256}}, {"name": "nucleus", "x1": 107, "y1": 64, "x2": 116, "y2": 77, "size": {"height": 256, "width": 256}}, {"name": "nucleus", "x1": 194, "y1": 108, "x2": 204, "y2": 114, "size": {"height": 256, "width": 256}}, {"name": "nucleus", "x1": 105, "y1": 82, "x2": 111, "y2": 91, "size": {"height": 256, "width": 256}}, {"name": "positive_cell", "x1": 90, "y1": 76, "x2": 111, "y2": 94, "size": {"height": 256, "width": 256}}, {"name": "nucleus", "x1": 58, "y1": 228, "x2": 74, "y2": 243, "size": {"height": 256, "width": 256}}, {"name": "nucleus", "x1": 135, "y1": 48, "x2": 143, "y2": 55, "size": {"height": 256, "width": 256}}, {"name": "nucleus", "x1": 153, "y1": 23, "x2": 160, "y2": 28, "size": {"height": 256, "width": 256}}, {"name": "positive_cell", "x1": 169, "y1": 113, "x2": 186, "y2": 138, "size": {"height": 256, "width": 256}}, {"name": "positive_cell", "x1": 207, "y1": 20, "x2": 226, "y2": 43, "size": {"height": 256, "width": 256}}, {"name": "positive_cell", "x1": 103, "y1": 79, "x2": 112, "y2": 92, "size": {"height": 256, "width": 256}}, {"name": "nucleus", "x1": 185, "y1": 224, "x2": 201, "y2": 231, "size": {"height": 256, "width": 256}}]}