{"labels": [{"name": "nucleus", "x1": 75, "y1": 27, "x2": 90, "y2": 46, "size": {"height": 256, "width": 256}}, {"name": "nucleus", "x1": 98, "y1": 37, "x2": 108, "y2": 61, "size": {"height": 256, "width": 256}}, {"name": "nucleus", "x1": 87, "y1": 74, "x2": 100, "y2": 102, "size": {"height": 256, "width": 256}}, {"name": "nucleus", "x1": 102, "y1": 175, "x2": 113, "y2": 194, "size": {"height": 256, "width": 256}}, {"name": "nucleus", "x1": 58, "y1": 108, "x2": 72, "y2": 121, "size": {"height": 256, "width": 256}}, {"name": "nucleus", "x1": 147, "y1": 112, "x2": 158, "y2": 141, "size": {"height": 256, "width": 256}}, {"name": "positive_cell", "x1": 89, "y1": 119, "x2": 105, "y2": 141, "size": {"height": 256, "width": 256}}, {"name": "positive_cell", "x1": 1, "y1": 198, "x2": 13, "y2": 242, "size": {"height": 256, "width": 256}}, {"name": "nucleus", "x1": 90, "y1": 122, "x2": 104, "y2": 141, "size": {"height": 256, "width": 256}}, {"name": "nucleus", "x1": 101, "y1": 115, "x2": 109, "y2": 128, "size": {"height": 256, "width": 256}}]}