{"labels": [{"name": "positive_cell", "x1": 134, "y1": 21, "x2": 157, "y2": 46, "size": {"height": 256, "width": 256}}, {"name": "nucleus", "x1": 165, "y1": 247, "x2": 179, "y2": 254, "size": {"height": 256, "width": 256}}, {"name": "nucleus", "x1": 214, "y1": 165, "x2": 233, "y2": 178, "size": {"height": 256, "width": 256}}, {"name": "nucleus", "x1": 140, "y1": 60, "x2": 152, "y2": 69, "size": {"height": 256, "width": 256}}, {"name": "nucleus", "x1": 194, "y1": 97, "x2": 211, "y2": 108, "size": {"height": 256, "width": 256}}, {"name": "nucleus", "x1": 199, "y1": 2, "x2": 212, "y2": 12, "size": {"height": 256, "width": 256}}, {"name": "nucleus", "x1": 18, "y1": 17, "x2": 26, "y2": 28, "size": {"height": 256, "width": 256}}, {"name": "nucleus", "x1": 137, "y1": 24, "x2": 154, "y2": 44, "size": {"height": 256, "width": 256}}]}