{"labels": [{"name": "nucleus", "x1": 239, "y1": 146, "x2": 250, "y2": 160, "size": {"height": 256, "width": 256}}, {"name": "nucleus", "x1": 220, "y1": 123, "x2": 237, "y2": 130, "size": {"height": 256, "width": 256}}, {"name": "nucleus", "x1": 190, "y1": 16, "x2": 197, "y2": 26, "size": {"height": 256, "width": 256}}, {"name": "nucleus", "x1": 7, "y1": 13, "x2": 16, "y2": 22, "size": {"height": 256, "width": 256}}, {"name": "positive_cell", "x1": 216, "y1": 124, "x2": 239, "y2": 141, "size": {"height": 256, "width": 256}}, {"name": "positive_cell", "x1": 228, "y1": 132, "x2": 239, "y2": 142, "size": {"height": 256, "width": 256}}, {"name": "nucleus", "x1": 200, "y1": 3, "x2": 208, "y2": 13, "size": {"height": 256, "width": 256}}, {"name": "nucleus", "x1": 136, "y1": 38, "x2": 143, "y2": 45, "size": {"height": 256, "width": 256}}, {"name": "nucleus", "x1": 189, "y1": 31, "x2": 194, "y2": 36, "size": {"height": 256, "width": 256}}]}