{"labels": [{"name": "nucleus", "x1": 48, "y1": 186, "x2": 63, "y2": 215, "size": {"height": 256, "width": 256}}, {"name": "nucleus", "x1": 75, "y1": 144, "x2": 90, "y2": 166, "size": {"height": 256, "width": 256}}, {"name": "nucleus", "x1": 80, "y1": 97, "x2": 91, "y2": 121, "size": {"height": 256, "width": 256}}, {"name": "nucleus", "x1": 115, "y1": 151, "x2": 127, "y2": 177, "size": {"height": 256, "width": 256}}, {"name": "nucleus", "x1": 79, "y1": 181, "x2": 87, "y2": 198, "size": {"height": 256, "width": 256}}, {"name": "nucleus", "x1": 67, "y1": 216, "x2": 78, "y2": 227, "size": {"height": 256, "width": 256}}, {"name": "nucleus", "x1": 91, "y1": 245, "x2": 99, "y2": 255, "size": {"height": 256, "width": 256}}]}