{"labels": [{"name": "nucleus", "x1": 56, "y1": 18, "x2": 72, "y2": 34, "size": {"height": 256, "width": 256}}, {"name": "nucleus", "x1": 32, "y1": 107, "x2": 50, "y2": 125, "size": {"height": 256, "width": 256}}, {"name": "nucleus", "x1": 128, "y1": 13, "x2": 144, "y2": 30, "size": {"height": 256, "width": 256}}, {"name": "nucleus", "x1": 68, "y1": 133, "x2": 82, "y2": 150, "size": {"height": 256, "width": 256}}, {"name": "nucleus", "x1": 73, "y1": 37, "x2": 84, "y2": 58, "size": {"height": 256, "width": 256}}, {"name": "nucleus", "x1": 208, "y1": 137, "x2": 222, "y2": 147, "size": {"height": 256, "width": 256}}, {"name": "nucleus", "x1": 95, "y1": 126, "x2": 109, "y2": 138, "size": {"height": 256, "width": 256}}, {"name": "nucleus", "x1": 168, "y1": 155, "x2": 187, "y2": 184, "size": {"height": 256, "width": 256}}, {"name": "positive_cell", "x1": 91, "y1": 229, "x2": 110, "y2": 251, "size": {"height": 256, "width": 256}}, {"name": "nucleus", "x1": 94, "y1": 229, "x2": 110, "y2": 253, "size": {"height": 256, "width": 256}}]}