{"labels": [{"name": "nucleus", "x1": 48, "y1": 58, "x2": 61, "y2": 69, "size": {"height": 256, "width": 256}}, {"name": "nucleus", "x1": 24, "y1": 170, "x2": 33, "y2": 179, "size": {"height": 256, "width": 256}}, {"name": "nucleus", "x1": 84, "y1": 111, "x2": 91, "y2": 116, "size": {"height": 256, "width": 256}}, {"name": "nucleus", "x1": 39, "y1": 152, "x2": 48, "y2": 165, "size": {"height": 256, "width": 256}}, {"name": "positive_cell", "x1": 18, "y1": 36, "x2": 38, "y2": 52, "size": {"height": 256, "width": 256}}, {"name": "nucleus", "x1": 40, "y1": 157, "x2": 48, "y2": 164, "size": {"height": 256, "width": 256}}]}