{"labels": [{"name": "positive_cell", "x1": 1, "y1": 223, "x2": 30, "y2": 246, "size": {"height": 256, "width": 256}}, {"name": "positive_cell", "x1": 69, "y1": 148, "x2": 80, "y2": 157, "size": {"height": 256, "width": 256}}, {"name": "nucleus", "x1": 189, "y1": 174, "x2": 201, "y2": 183, "size": {"height": 256, "width": 256}}, {"name": "nucleus", "x1": 145, "y1": 146, "x2": 150, "y2": 149, "size": {"height": 256, "width": 256}}, {"name": "nucleus", "x1": 171, "y1": 159, "x2": 178, "y2": 167, "size": {"height": 256, "width": 256}}, {"name": "nucleus", "x1": 70, "y1": 150, "x2": 78, "y2": 157, "size": {"height": 256, "width": 256}}]}