{"labels": [{"name": "nucleus", "x1": 7, "y1": 105, "x2": 27, "y2": 119, "size": {"height": 256, "width": 256}}, {"name": "nucleus", "x1": 0, "y1": 115, "x2": 14, "y2": 129, "size": {"height": 256, "width": 256}}, {"name": "nucleus", "x1": 74, "y1": 218, "x2": 83, "y2": 231, "size": {"height": 256, "width": 256}}, {"name": "nucleus", "x1": 102, "y1": 210, "x2": 126, "y2": 218, "size": {"height": 256, "width": 256}}, {"name": "nucleus", "x1": 196, "y1": 112, "x2": 206, "y2": 123, "size": {"height": 256, "width": 256}}, {"name": "nucleus", "x1": 137, "y1": 73, "x2": 147, "y2": 89, "size": {"height": 256, "width": 256}}, {"name": "nucleus", "x1": 34, "y1": 30, "x2": 43, "y2": 41, "size": {"height": 256, "width": 256}}, {"name": "nucleus", "x1": 197, "y1": 75, "x2": 207, "y2": 84, "size": {"height": 256, "width": 256}}, {"name": "nucleus", "x1": 41, "y1": 92, "x2": 58, "y2": 107, "size": {"height": 256, "width": 256}}, {"name": "nucleus", "x1": 76, "y1": 24, "x2": 95, "y2": 48, "size": {"height": 256, "width": 256}}, {"name": "nucleus", "x1": 184, "y1": 60, "x2": 190, "y2": 67, "size": {"height": 256, "width": 256}}, {"name": "nucleus", "x1": 170, "y1": 40, "x2": 177, "y2": 47, "size": {"height": 256, "width": 256}}, {"name": "nucleus", "x1": 1, "y1": 55, "x2": 14, "y2": 64, "size": {"height": 256, "width": 256}}, {"name": "nucleus", "x1": 92, "y1": 165, "x2": 99, "y2": 169, "size": {"height": 256, "width": 256}}]}