{"labels": [{"name": "nucleus", "x1": 218, "y1": 100, "x2": 227, "y2": 110, "size": {"height": 256, "width": 256}}, {"name": "nucleus", "x1": 151, "y1": 206, "x2": 159, "y2": 221, "size": {"height": 256, "width": 256}}, {"name": "positive_cell", "x1": 189, "y1": 151, "x2": 214, "y2": 168, "size": {"height": 256, "width": 256}}, {"name": "nucleus", "x1": 191, "y1": 158, "x2": 207, "y2": 167, "size": {"height": 256, "width": 256}}, {"name": "nucleus", "x1": 191, "y1": 151, "x2": 212, "y2": 167, "size": {"height": 256, "width": 256}}]}