{"labels": [{"name": "nucleus", "x1": 155, "y1": 110, "x2": 168, "y2": 127, "size": {"height": 256, "width": 256}}, {"name": "nucleus", "x1": 231, "y1": 114, "x2": 248, "y2": 122, "size": {"height": 256, "width": 256}}, {"name": "nucleus", "x1": 195, "y1": 191, "x2": 206, "y2": 201, "size": {"height": 256, "width": 256}}, {"name": "nucleus", "x1": 247, "y1": 94, "x2": 254, "y2": 104, "size": {"height": 256, "width": 256}}, {"name": "nucleus", "x1": 211, "y1": 170, "x2": 223, "y2": 185, "size": {"height": 256, "width": 256}}, {"name": "nucleus", "x1": 206, "y1": 108, "x2": 213, "y2": 114, "size": {"height": 256, "width": 256}}, {"name": "nucleus", "x1": 176, "y1": 106, "x2": 186, "y2": 110, "size": {"height": 256, "width": 256}}, {"name": "nucleus", "x1": 166, "y1": 62, "x2": 173, "y2": 69, "size": {"height": 256, "width": 256}}, {"name": "nucleus", "x1": 124, "y1": 228, "x2": 152, "y2": 240, "size": {"height": 256, "width": 256}}]}